odoo8_addon_web_widget_url_listview-8.0.1.0.0.99.dev1-py2.7-nspkg.pth
odoo8_addon_web_widget_url_listview-8.0.1.0.0.99.dev1.dist-info/METADATA
odoo8_addon_web_widget_url_listview-8.0.1.0.0.99.dev1.dist-info/RECORD
odoo8_addon_web_widget_url_listview-8.0.1.0.0.99.dev1.dist-info/WHEEL
odoo8_addon_web_widget_url_listview-8.0.1.0.0.99.dev1.dist-info/namespace_packages.txt
odoo8_addon_web_widget_url_listview-8.0.1.0.0.99.dev1.dist-info/top_level.txt
odoo_addons/web_widget_url_listview/README.rst
odoo_addons/web_widget_url_listview/__init__.py
odoo_addons/web_widget_url_listview/__openerp__.py
odoo_addons/web_widget_url_listview/data/assets_backend.xml
odoo_addons/web_widget_url_listview/demo/demo.xml
odoo_addons/web_widget_url_listview/i18n/web_widget_url_listview.pot
odoo_addons/web_widget_url_listview/static/description/icon.png
odoo_addons/web_widget_url_listview/static/src/js/web_list_url_widget.js
